<?xml version="1.0"?>
<!--
  Licensed to the Apache Software Foundation (ASF) under one or more
  contributor license agreements.  See the NOTICE file distributed with
  this work for additional information regarding copyright ownership.
  The ASF licenses this file to You under the Apache License, Version 2.0
  (the "License"); you may not use this file except in compliance with
  the License.  You may obtain a copy of the License at

      http://www.apache.org/licenses/LICENSE-2.0

  Unless required by applicable law or agreed to in writing, software
  distributed under the License is distributed on an "AS IS" BASIS,
  WITHOUT WARRANTIES OR CONDITIONS OF ANY KIND, either express or implied.
  See the License for the specific language governing permissions and
  limitations under the License.
-->
<!--+
    | This is a sample configuration for layout types.
    |
    | @version $Id$
    +-->
<beans xmlns="http://www.springframework.org/schema/beans"
       xmlns:xsi="http://www.w3.org/2001/XMLSchema-instance"
       xmlns:portal="http://cocoon.apache.org/schema/portal"
       xsi:schemaLocation="http://www.springframework.org/schema/beans http://www.springframework.org/schema/beans/spring-beans-2.5.xsd
                           http://www.springframework.org/schema/util http://www.springframework.org/schema/util/spring-util-2.5.xsd
                           http://cocoon.apache.org/schema/portal http://cocoon.apache.org/schema/portal/cocoon-portal-1.0.xsd">

    <portal:coplet-type id="uri">
      <portal:coplet-adapter type="cocoon"/>
    </portal:coplet-type>
    
    <portal:coplet-type id="portlet">
      <!-- FIXME - this should be portlet, but we need to convert the portlet module
                   to Spring first -->
      <portal:coplet-adapter type="cocoon"/>
      <portal:configuration name="buffer" type="boolean" value="true"/>
      <portal:configuration name="full-screen" type="boolean" value="false"/>
      <portal:configuration name="handle-sizing" type="boolean" value="true"/>
    </portal:coplet-type>

<!-- 
    <portal:coplet-type id="wsrp">
      <portal:coplet-adapter type="wsrp"/>
      <portal:configuration name="buffer" type="boolean" value="true"/>
    </portal:coplet-type>
 -->
</beans>