<?xml version="1.0" encoding="UTF-8"?>
<page>
  <title>Formvalidation and -prefilling</title>
  <content>

    <para>
      The entered data successfully passed the validation stage.
    </para>


    <form name="car" method="post">
       <para>
         A <input type="text" name="type" readonly="true"/> car which seats
		 <input type="text" name="persons" readonly="true"/> has been reserved for you.
         Please leave the deposit of EUR <input type="text" name="deposit" readonly="true"/>
		 at the reception. The invoice will be send to <textarea name="address"/> and a
		 confirmation email will be send to <input type="text" readonly="true" name="email"/>. Thank you.
       </para>
    </form>

  </content>
</page>
